HISTORY.rst
LICENSE
MANIFEST.in
README.rst
VERSION
requirements.txt
setup.cfg
setup.py
src/scrapy_redis/__init__.py
src/scrapy_redis/connection.py
src/scrapy_redis/defaults.py
src/scrapy_redis/dupefilter.py
src/scrapy_redis/picklecompat.py
src/scrapy_redis/pipelines.py
src/scrapy_redis/queue.py
src/scrapy_redis/scheduler.py
src/scrapy_redis/spiders.py
src/scrapy_redis/stats.py
src/scrapy_redis/utils.py
src/zcbot_scrapy_redis.egg-info/PKG-INFO
src/zcbot_scrapy_redis.egg-info/SOURCES.txt
src/zcbot_scrapy_redis.egg-info/dependency_links.txt
src/zcbot_scrapy_redis.egg-info/requires.txt
src/zcbot_scrapy_redis.egg-info/top_level.txt