Metadata-Version: 2.1
Name: zcbot-scrapy-redis
Version: 0.7.3.2110.2.2
Summary: Redis-based components for Scrapy 2.11.0+.
Home-page: https://github.com/rolando/scrapy-redis
Author: zsodata
Author-email: rolando@rmax.io
License: MIT
Keywords: scrapy-redis
Classifier: Development Status :: 4 - Beta
Classifier: Intended Audience :: Developers
Classifier: License :: OSI Approved :: MIT License
Classifier: Natural Language :: English
Classifier: Programming Language :: Python :: 3
Classifier: Programming Language :: Python :: 3.7
Classifier: Programming Language :: Python :: 3.8
Classifier: Programming Language :: Python :: 3.9
Classifier: Programming Language :: Python :: 3.10
License-File: LICENSE
